snap_analog-2.1.0.dist-info/licenses/LICENSE
src/__init__.py
src/cli.py
src/log_analyzer.py
src/log_visualizer.py
snap_analog-2.1.0.dist-info/METADATA
snap_analog-2.1.0.dist-info/WHEEL
snap_analog-2.1.0.dist-info/entry_points.txt
snap_analog-2.1.0.dist-info/top_level.txt
snap_analog-2.1.0.dist-info/RECORD
